{
  "manifestVersion": 1,
  "publisher": "felipetoffoli",
  "version": "1.0.93",
  "public": true,
  "id": "azdo-library-env-react",
  "name": "Library .env Tools",
  "description": "Importa e exporta bibliotecas como arquivos .env",
  "categories": ["Azure Pipelines"],
  "targets": [{ "id": "Microsoft.VisualStudio.Services" }],
  "icons": { "default": "icon.png" },
   "content": {"details": {"path": "README.md"}},
  "files": [
    { "path": "static", "addressable": true },
    { "path": "dist", "addressable": true },
    { "path": "docs/screenshots", "addressable": true }
  ],
  "links": {
    "home": {
      "uri": "https://marketplace.visualstudio.com/publishers/felipetoffoli"
    },
    "repository": {
      "uri": "https://github.com/felipetoffoli/import-export-azure-devops-libary"
    },
    "issues": {
      "uri": "https://github.com/felipetoffoli/import-export-azure-devops-libary/issues"
    }
  }
  
}

